lazperf/pylazperfapi.cpython-37m-x86_64-linux-gnu.so
lazperf/pylazperfapi.cpp
lazperf/PyVlrCompressor.cpp
lazperf/__init__.py
lazperf/PyLazperf.cpp
lazperf-1.5.dist-info/WHEEL
lazperf-1.5.dist-info/COPYING
lazperf-1.5.dist-info/top_level.txt
lazperf-1.5.dist-info/RECORD
lazperf-1.5.dist-info/METADATA
