Metadata-Version: 2.1
Name: lazperf
Version: 1.5
Summary: Point cloud data compression
Home-page: https://github.com/hobu/laz-perf
Author: Howard Butler
Author-email: howard@hobu.co
Maintainer: Howard Butler
Maintainer-email: howard@hobu.co
License: LGPL
Keywords: point cloud compression
Platform: UNKNOWN
Classifier: Development Status :: 4 - Beta
Classifier: Intended Audience :: Developers
Classifier: Intended Audience :: Science/Research
Classifier: License :: OSI Approved :: GNU Lesser General Public License v2 (LGPLv2)
Classifier: Operating System :: OS Independent
Classifier: Programming Language :: Python :: 2.7
Classifier: Programming Language :: Python :: 3
Classifier: Topic :: Scientific/Engineering :: GIS
